cdk_iot_core_certficates/__init__.py
cdk_iot_core_certficates/py.typed
cdk_iot_core_certficates/_jsii/__init__.py
cdk_iot_core_certficates/_jsii/cdk-iot-core-certificates@1.0.75.jsii.tgz
cdk_iot_core_certificates-1.0.75.dist-info/LICENSE
cdk_iot_core_certificates-1.0.75.dist-info/METADATA
cdk_iot_core_certificates-1.0.75.dist-info/WHEEL
cdk_iot_core_certificates-1.0.75.dist-info/top_level.txt
cdk_iot_core_certificates-1.0.75.dist-info/RECORD
